Metadata-Version: 2.1
Name: riotkit.pbs
Version: 1.0
Summary: Python Build Simplified. A simple setuptools automation, designed mainly for publishing multiple packages from single repository
Home-page: https://github.com/riotkit-org
Author-email: riotkit@riseup.net
License: Apache-2
Keywords: riotkit,pbs,pbr,build,simplified,reasonable,setuptools,anarchist,namespace,namespaced
Platform: UNKNOWN
